LICENSE
MANIFEST.in
README.rst
pytest.ini
requirements-dev.txt
requirements.txt
setup.cfg
setup.py
nsot/__init__.py
nsot/admin.py
nsot/exc.py
nsot/fields.py
nsot/validators.py
nsot/version.py
nsot/wsgi.py
nsot.egg-info/PKG-INFO
nsot.egg-info/SOURCES.txt
nsot.egg-info/dependency_links.txt
nsot.egg-info/entry_points.txt
nsot.egg-info/requires.txt
nsot.egg-info/top_level.txt
nsot/api/__init__.py
nsot/api/auth.py
nsot/api/filters.py
nsot/api/renderers.py
nsot/api/routers.py
nsot/api/serializers.py
nsot/api/urls.py
nsot/api/views.py
nsot/conf/__init__.py
nsot/conf/settings.py
nsot/conf/urls.py
nsot/management/__init__.py
nsot/management/commands/__init__.py
nsot/management/commands/generate_key.py
nsot/management/commands/start.py
nsot/management/commands/upgrade.py
nsot/management/commands/user_proxy.py
nsot/middleware/__init__.py
nsot/middleware/auth.py
nsot/middleware/request_logging.py
nsot/migrations/0001_initial.py
nsot/migrations/0002_auto_20150810_1718.py
nsot/migrations/0003_auto_20150810_1751.py
nsot/migrations/0004_auto_20150810_1806.py
nsot/migrations/0005_auto_20150810_1847.py
nsot/migrations/0006_auto_20150810_1947.py
nsot/migrations/0007_auto_20150811_1201.py
nsot/migrations/0008_auto_20150811_1222.py
nsot/migrations/0009_auto_20150811_1245.py
nsot/migrations/0010_auto_20150921_2120.py
nsot/migrations/0011_auto_20150930_1557.py
nsot/migrations/0012_auto_20151002_1427.py
nsot/migrations/0013_auto_20151002_1443.py
nsot/migrations/0014_auto_20151002_1653.py
nsot/migrations/0015_move_attribute_fields.py
nsot/migrations/0016_move_device_data.py
nsot/migrations/0017_move_network_data.py
nsot/migrations/0018_move_interface_data.py
nsot/migrations/0019_move_assignment_data.py
nsot/migrations/0020_move_value_data.py
nsot/migrations/0021_remove_resource_object.py
nsot/migrations/0022_auto_20151007_1847.py
nsot/migrations/0023_auto_20151008_1351.py
nsot/migrations/0024_network_state.py
nsot/migrations/0025_value_site.py
nsot/migrations/0026_model_field_verbose_names.py
nsot/migrations/0027_interface_device_hostname.py
nsot/migrations/0028_populate_interface_device_hostname.py
nsot/migrations/0029_auto__add_circuit.py
