Metadata-Version: 1.2
Name: nsot
Version: 1.4.6
Summary: Network Source of Truth (IP Address Management).
Home-page: https://github.com/dropbox/nsot
Author: Gary M. Josack
Author-email: gary@dropbox.com
Maintainer: Gary M. Josack
Maintainer-email: gary@dropbox.com
License: Apache
Platform: UNKNOWN
Classifier: Programming Language :: Python
Classifier: Topic :: Software Development
Classifier: Topic :: Software Development :: Libraries
Classifier: Topic :: Software Development :: Libraries :: Python Modules
